{
  "source_file": "all_valid_levels\\levels_ge__lvl-217__e4295be7.txt",
  "operator": "multi_round_corrupt",
  "severity": null,
  "seed": 3467,
  "attempts_tried": 1,
  "attempt_summaries": [
    {
      "attempt": 1,
      "summary": {
        "rounds": 1,
        "edits": 29
      }
    }
  ],
  "op": "multi_round_corrupt",
  "changed": [
    [
      54,
      15
    ],
    [
      147,
      15
    ],
    [
      96,
      15
    ],
    [
      1,
      15
    ],
    [
      169,
      15
    ],
    [
      142,
      15
    ],
    [
      111,
      15
    ],
    [
      197,
      15
    ],
    [
      86,
      15
    ],
    [
      92,
      15
    ],
    [
      27,
      15
    ],
    [
      87,
      15
    ],
    [
      131,
      15
    ],
    [
      175,
      15
    ],
    [
      0,
      15
    ],
    [
      94,
      15
    ],
    [
      80,
      15
    ],
    [
      150,
      15
    ],
    [
      51,
      15
    ],
    [
      88,
      15
    ],
    [
      125,
      15
    ],
    [
      70,
      15
    ],
    [
      121,
      15
    ],
    [
      128,
      15
    ],
    [
      178,
      15
    ],
    [
      12,
      15
    ],
    [
      40,
      15
    ],
    [
      3,
      15
    ],
    [
      61,
      15
    ]
  ],
  "plan": {
    "rounds": 3,
    "per_round": [
      {
        "round": 1,
        "pattern": "remove_identical",
        "k": 29,
        "details": {
          "tile": "X"
        },
        "edits_applied": 29
      }
    ]
  }
}