{
  "source_file": "all_valid_levels\\levels_notch__lvl-727__af1d74b0.txt",
  "operator": "op_remove_or_move_F",
  "severity": 1,
  "seed": 5503,
  "attempts_tried": 3,
  "attempt_summaries": [
    {
      "attempt": 1,
      "summary": {
        "rounds": 2,
        "edits": 20
      }
    },
    {
      "attempt": 2,
      "summary": {
        "rounds": 3,
        "edits": 64
      }
    },
    {
      "attempt": 3,
      "summary": {
        "rounds": 5,
        "edits": 151
      }
    }
  ],
  "op": "remove_or_move_F",
  "changed": [
    [
      151,
      13
    ],
    [
      194,
      13
    ],
    [
      195,
      13
    ],
    [
      196,
      13
    ],
    [
      197,
      13
    ]
  ]
}